<?xml version="1.0" encoding="utf-8"?>
<scriptinfo>
  <settings global="False" successfully="True" compiled="False">
    <name>maps\mp\gametypes\_gameobjects</name>
  </settings>
  <content>
    <include>maps\mp\_utility</include>
    <include>maps\mp\gametypes\_hud_util</include>
    <include>common_scripts\utility</include>
    <func name="main" access="Public">
      <self>
      </self>
      <summary>
      </summary>
      <returns>
      </returns>
      <example>
      </example>
      <param name="allowed">
      </param>
    </func>
    <func name="init" access="Public">
      <self>
      </self>
      <summary>
      </summary>
      <returns>
      </returns>
      <example>
      </example>
    </func>
    <func name="onPlayerConnect" access="Public">
      <self>
      </self>
      <summary>
      </summary>
      <returns>
      </returns>
      <example>
      </example>
    </func>
    <func name="onPlayerSpawned" access="Public">
      <self>
      </self>
      <summary>
      </summary>
      <returns>
      </returns>
      <example>
      </example>
    </func>
    <func name="onDeath" access="Public">
      <self>
      </self>
      <summary>
      </summary>
      <returns>
      </returns>
      <example>
      </example>
    </func>
    <func name="onDisconnect" access="Public">
      <self>
      </self>
      <summary>
      </summary>
      <returns>
      </returns>
      <example>
      </example>
    </func>
    <func name="createCarryObject" access="Public">
      <self>
      </self>
      <summary>
      </summary>
      <returns>
      </returns>
      <example>
      </example>
      <param name="ownerTeam">
      </param>
      <param name="trigger">
      </param>
      <param name="visuals">
      </param>
      <param name="offset">
      </param>
    </func>
    <func name="carryObjectUseThink" access="Public">
      <self>
      </self>
      <summary>
      </summary>
      <returns>
      </returns>
      <example>
      </example>
    </func>
    <func name="carryObjectProxThink" access="Public">
      <self>
      </self>
      <summary>
      </summary>
      <returns>
      </returns>
      <example>
      </example>
    </func>
    <func name="pickupManual" access="Public">
      <self>
      </self>
      <summary>
      </summary>
      <returns>
      </returns>
      <example>
      </example>
      <param name="player">
      </param>
    </func>
    <func name="resetPickupManualFlag" access="Public">
      <self>
      </self>
      <summary>
      </summary>
      <returns>
      </returns>
      <example>
      </example>
      <param name="player">
      </param>
    </func>
    <func name="resetPickupManualFlagOnDeath" access="Public">
      <self>
      </self>
      <summary>
      </summary>
      <returns>
      </returns>
      <example>
      </example>
      <param name="player">
      </param>
    </func>
    <func name="pickupObjectDelay" access="Public">
      <self>
      </self>
      <summary>
      </summary>
      <returns>
      </returns>
      <example>
      </example>
      <param name="origin">
      </param>
    </func>
    <func name="pickupObjectDelayTime" access="Public">
      <self>
      </self>
      <summary>
      </summary>
      <returns>
      </returns>
      <example>
      </example>
      <param name="timeToWait">
      </param>
    </func>
    <func name="setPickedUp" access="Public">
      <self>
      </self>
      <summary>
      </summary>
      <returns>
      </returns>
      <example>
      </example>
      <param name="player">
      </param>
    </func>
    <func name="updateCarryObjectOrigin" access="Public">
      <self>
      </self>
      <summary>
      </summary>
      <returns>
      </returns>
      <example>
      </example>
    </func>
    <func name="giveObject" access="Public">
      <self>
      </self>
      <summary>
      </summary>
      <returns>
      </returns>
      <example>
      </example>
      <param name="object">
      </param>
    </func>
    <func name="returnHome" access="Public">
      <self>
      </self>
      <summary>
      </summary>
      <returns>
      </returns>
      <example>
      </example>
      <param name="player">
      </param>
    </func>
    <func name="setPosition" access="Public">
      <self>
      </self>
      <summary>
      </summary>
      <returns>
      </returns>
      <example>
      </example>
      <param name="origin">
      </param>
      <param name="angles">
      </param>
    </func>
    <func name="onPlayerLastStand" access="Public">
      <self>
      </self>
      <summary>
      </summary>
      <returns>
      </returns>
      <example>
      </example>
    </func>
    <func name="setDropped" access="Public">
      <self>
      </self>
      <summary>
      </summary>
      <returns>
      </returns>
      <example>
      </example>
    </func>
    <func name="setCarrier" access="Public">
      <self>
      </self>
      <summary>
      </summary>
      <returns>
      </returns>
      <example>
      </example>
      <param name="carrier">
      </param>
    </func>
    <func name="clearCarrier" access="Public">
      <self>
      </self>
      <summary>
      </summary>
      <returns>
      </returns>
      <example>
      </example>
    </func>
    <func name="pickupTimeout" access="Public">
      <self>
      </self>
      <summary>
      </summary>
      <returns>
      </returns>
      <example>
      </example>
    </func>
    <func name="takeObject" access="Public">
      <self>
      </self>
      <summary>
      </summary>
      <returns>
      </returns>
      <example>
      </example>
      <param name="object">
      </param>
    </func>
    <func name="trackCarrier" access="Public">
      <self>
      </self>
      <summary>
      </summary>
      <returns>
      </returns>
      <example>
      </example>
    </func>
    <func name="manualDropThink" access="Public">
      <self>
      </self>
      <summary>
      </summary>
      <returns>
      </returns>
      <example>
      </example>
    </func>
    <func name="createUseObject" access="Public">
      <self>
      </self>
      <summary>
      </summary>
      <returns>
      </returns>
      <example>
      </example>
      <param name="ownerTeam">
      </param>
      <param name="trigger">
      </param>
      <param name="visuals">
      </param>
      <param name="offset">
      </param>
    </func>
    <func name="setKeyObject" access="Public">
      <self>
      </self>
      <summary>
      </summary>
      <returns>
      </returns>
      <example>
      </example>
      <param name="object">
      </param>
    </func>
    <func name="useObjectUseThink" access="Public">
      <self>
      </self>
      <summary>
      </summary>
      <returns>
      </returns>
      <example>
      </example>
    </func>
    <func name="getEarliestClaimPlayer" access="Public">
      <self>
      </self>
      <summary>
      </summary>
      <returns>
      </returns>
      <example>
      </example>
    </func>
    <func name="useObjectProxThink" access="Public">
      <self>
      </self>
      <summary>
      </summary>
      <returns>
      </returns>
      <example>
      </example>
    </func>
    <func name="proxTriggerThink" access="Public">
      <self>
      </self>
      <summary>
      </summary>
      <returns>
      </returns>
      <example>
      </example>
    </func>
    <func name="setClaimTeam" access="Public">
      <self>
      </self>
      <summary>
      </summary>
      <returns>
      </returns>
      <example>
      </example>
      <param name="newTeam">
      </param>
    </func>
    <func name="getClaimTeam" access="Public">
      <self>
      </self>
      <summary>
      </summary>
      <returns>
      </returns>
      <example>
      </example>
    </func>
    <func name="triggerTouchThink" access="Public">
      <self>
      </self>
      <summary>
      </summary>
      <returns>
      </returns>
      <example>
      </example>
      <param name="object">
      </param>
    </func>
    <func name="updateProxBar" access="Public">
      <self>
      </self>
      <summary>
      </summary>
      <returns>
      </returns>
      <example>
      </example>
      <param name="object">
      </param>
      <param name="forceRemove">
      </param>
    </func>
    <func name="updateUseRate" access="Public">
      <self>
      </self>
      <summary>
      </summary>
      <returns>
      </returns>
      <example>
      </example>
    </func>
    <func name="attachUseModel" access="Public">
      <self>
      </self>
      <summary>
      </summary>
      <returns>
      </returns>
      <example>
      </example>
      <param name="modelName">
      </param>
      <param name="tagName">
      </param>
      <param name="ignoreCollision">
      </param>
    </func>
    <func name="useHoldThink" access="Public">
      <self>
      </self>
      <summary>
      </summary>
      <returns>
      </returns>
      <example>
      </example>
      <param name="player">
      </param>
    </func>
    <func name="detachUseModels" access="Public">
      <self>
      </self>
      <summary>
      </summary>
      <returns>
      </returns>
      <example>
      </example>
    </func>
    <func name="takeUseWeapon" access="Public">
      <self>
      </self>
      <summary>
      </summary>
      <returns>
      </returns>
      <example>
      </example>
      <param name="useWeapon">
      </param>
    </func>
    <func name="useHoldThinkLoop" access="Public">
      <self>
      </self>
      <summary>
      </summary>
      <returns>
      </returns>
      <example>
      </example>
      <param name="player">
      </param>
      <param name="lastWeapon">
      </param>
    </func>
    <func name="personalUseBar" access="Public">
      <self>
      </self>
      <summary>
      </summary>
      <returns>
      </returns>
      <example>
      </example>
      <param name="object">
      </param>
    </func>
    <func name="updateTrigger" access="Public">
      <self>
      </self>
      <summary>
      </summary>
      <returns>
      </returns>
      <example>
      </example>
    </func>
    <func name="updateWorldIcons" access="Public">
      <self>
      </self>
      <summary>
      </summary>
      <returns>
      </returns>
      <example>
      </example>
    </func>
    <func name="updateWorldIcon" access="Public">
      <self>
      </self>
      <summary>
      </summary>
      <returns>
      </returns>
      <example>
      </example>
      <param name="relativeTeam">
      </param>
      <param name="showIcon">
      </param>
    </func>
    <func name="updateCompassIcons" access="Public">
      <self>
      </self>
      <summary>
      </summary>
      <returns>
      </returns>
      <example>
      </example>
    </func>
    <func name="updateCompassIcon" access="Public">
      <self>
      </self>
      <summary>
      </summary>
      <returns>
      </returns>
      <example>
      </example>
      <param name="relativeTeam">
      </param>
      <param name="showIcon">
      </param>
    </func>
    <func name="shouldPingObject" access="Public">
      <self>
      </self>
      <summary>
      </summary>
      <returns>
      </returns>
      <example>
      </example>
      <param name="relativeTeam">
      </param>
    </func>
    <func name="getUpdateTeams" access="Public">
      <self>
      </self>
      <summary>
      </summary>
      <returns>
      </returns>
      <example>
      </example>
      <param name="relativeTeam">
      </param>
    </func>
    <func name="shouldShowCompassDueToRadar" access="Public">
      <self>
      </self>
      <summary>
      </summary>
      <returns>
      </returns>
      <example>
      </example>
      <param name="team">
      </param>
    </func>
    <func name="updateVisibilityAccordingToRadar" access="Public">
      <self>
      </self>
      <summary>
      </summary>
      <returns>
      </returns>
      <example>
      </example>
    </func>
    <func name="setOwnerTeam" access="Public">
      <self>
      </self>
      <summary>
      </summary>
      <returns>
      </returns>
      <example>
      </example>
      <param name="team">
      </param>
    </func>
    <func name="getOwnerTeam" access="Public">
      <self>
      </self>
      <summary>
      </summary>
      <returns>
      </returns>
      <example>
      </example>
    </func>
    <func name="setUseTime" access="Public">
      <self>
      </self>
      <summary>
      </summary>
      <returns>
      </returns>
      <example>
      </example>
      <param name="time">
      </param>
    </func>
    <func name="setUseText" access="Public">
      <self>
      </self>
      <summary>
      </summary>
      <returns>
      </returns>
      <example>
      </example>
      <param name="text">
      </param>
    </func>
    <func name="setUseHintText" access="Public">
      <self>
      </self>
      <summary>
      </summary>
      <returns>
      </returns>
      <example>
      </example>
      <param name="text">
      </param>
    </func>
    <func name="allowCarry" access="Public">
      <self>
      </self>
      <summary>
      </summary>
      <returns>
      </returns>
      <example>
      </example>
      <param name="relativeTeam">
      </param>
    </func>
    <func name="allowUse" access="Public">
      <self>
      </self>
      <summary>
      </summary>
      <returns>
      </returns>
      <example>
      </example>
      <param name="relativeTeam">
      </param>
    </func>
    <func name="setVisibleTeam" access="Public">
      <self>
      </self>
      <summary>
      </summary>
      <returns>
      </returns>
      <example>
      </example>
      <param name="relativeTeam">
      </param>
    </func>
    <func name="setModelVisibility" access="Public">
      <self>
      </self>
      <summary>
      </summary>
      <returns>
      </returns>
      <example>
      </example>
      <param name="visibility">
      </param>
    </func>
    <func name="makeSolid" access="Public">
      <self>
      </self>
      <summary>
      </summary>
      <returns>
      </returns>
      <example>
      </example>
    </func>
    <func name="setCarrierVisible" access="Public">
      <self>
      </self>
      <summary>
      </summary>
      <returns>
      </returns>
      <example>
      </example>
      <param name="relativeTeam">
      </param>
    </func>
    <func name="setCanUse" access="Public">
      <self>
      </self>
      <summary>
      </summary>
      <returns>
      </returns>
      <example>
      </example>
      <param name="relativeTeam">
      </param>
    </func>
    <func name="set2DIcon" access="Public">
      <self>
      </self>
      <summary>
      </summary>
      <returns>
      </returns>
      <example>
      </example>
      <param name="relativeTeam">
      </param>
      <param name="shader">
      </param>
    </func>
    <func name="set3DIcon" access="Public">
      <self>
      </self>
      <summary>
      </summary>
      <returns>
      </returns>
      <example>
      </example>
      <param name="relativeTeam">
      </param>
      <param name="shader">
      </param>
    </func>
    <func name="set3DUseIcon" access="Public">
      <self>
      </self>
      <summary>
      </summary>
      <returns>
      </returns>
      <example>
      </example>
      <param name="relativeTeam">
      </param>
      <param name="shader">
      </param>
    </func>
    <func name="setCarryIcon" access="Public">
      <self>
      </self>
      <summary>
      </summary>
      <returns>
      </returns>
      <example>
      </example>
      <param name="shader">
      </param>
    </func>
    <func name="disableObject" access="Public">
      <self>
      </self>
      <summary>
      </summary>
      <returns>
      </returns>
      <example>
      </example>
    </func>
    <func name="enableObject" access="Public">
      <self>
      </self>
      <summary>
      </summary>
      <returns>
      </returns>
      <example>
      </example>
    </func>
    <func name="getRelativeTeam" access="Public">
      <self>
      </self>
      <summary>
      </summary>
      <returns>
      </returns>
      <example>
      </example>
      <param name="team">
      </param>
    </func>
    <func name="isFriendlyTeam" access="Public">
      <self>
      </self>
      <summary>
      </summary>
      <returns>
      </returns>
      <example>
      </example>
      <param name="team">
      </param>
    </func>
    <func name="canInteractWith" access="Public">
      <self>
      </self>
      <summary>
      </summary>
      <returns>
      </returns>
      <example>
      </example>
      <param name="team">
      </param>
    </func>
    <func name="isTeam" access="Public">
      <self>
      </self>
      <summary>
      </summary>
      <returns>
      </returns>
      <example>
      </example>
      <param name="team">
      </param>
    </func>
    <func name="isRelativeTeam" access="Public">
      <self>
      </self>
      <summary>
      </summary>
      <returns>
      </returns>
      <example>
      </example>
      <param name="relativeTeam">
      </param>
    </func>
    <func name="_disableWeapon" access="Public">
      <self>
      </self>
      <summary>
      </summary>
      <returns>
      </returns>
      <example>
      </example>
    </func>
    <func name="_enableWeapon" access="Public">
      <self>
      </self>
      <summary>
      </summary>
      <returns>
      </returns>
      <example>
      </example>
    </func>
    <func name="_disableSprint" access="Public">
      <self>
      </self>
      <summary>
      </summary>
      <returns>
      </returns>
      <example>
      </example>
    </func>
    <func name="_enableSprint" access="Public">
      <self>
      </self>
      <summary>
      </summary>
      <returns>
      </returns>
      <example>
      </example>
    </func>
    <func name="_disableJump" access="Public">
      <self>
      </self>
      <summary>
      </summary>
      <returns>
      </returns>
      <example>
      </example>
    </func>
    <func name="_enableJump" access="Public">
      <self>
      </self>
      <summary>
      </summary>
      <returns>
      </returns>
      <example>
      </example>
    </func>
    <func name="getEnemyTeam" access="Public">
      <self>
      </self>
      <summary>
      </summary>
      <returns>
      </returns>
      <example>
      </example>
      <param name="team">
      </param>
    </func>
    <func name="getNextObjID" access="Public">
      <self>
      </self>
      <summary>
      </summary>
      <returns>
      </returns>
      <example>
      </example>
    </func>
    <func name="resetObjID" access="Public">
      <self>
      </self>
      <summary>
      </summary>
      <returns>
      </returns>
      <example>
      </example>
      <param name="id">
      </param>
    </func>
    <func name="getLabel" access="Public">
      <self>
      </self>
      <summary>
      </summary>
      <returns>
      </returns>
      <example>
      </example>
    </func>
    <error type="semantic" charIndex="791" charLength="28" lineIndex="16">
      <message>Could not include file 'openwarfare\_utils'</message>
      <fullMessage>Bad semantic: Could not include file 'openwarfare\_utils', file 'maps\mp\gametypes\_gameobjects', line 17, '#include openwarfare\_utils;'</fullMessage>
    </error>
    <error type="semantic" charIndex="820" charLength="30" lineIndex="17">
      <message>Could not include file 'openwarfare\_logdata'</message>
      <fullMessage>Bad semantic: Could not include file 'openwarfare\_logdata', file 'maps\mp\gametypes\_gameobjects', line 18, '#include openwarfare\_logdata;'</fullMessage>
    </error>
  </content>
</scriptinfo>