<?xml version="1.0" encoding="utf-8"?>
<scriptinfo>
  <settings global="False" successfully="True" compiled="False">
    <name>maps\mp\_flashgrenades</name>
  </settings>
  <content>
    <func name="main" access="Public">
      <self>
      </self>
      <summary>
      </summary>
      <returns>
      </returns>
      <example>
      </example>
    </func>
    <func name="startMonitoringFlash" access="Public">
      <self>
      </self>
      <summary>
      </summary>
      <returns>
      </returns>
      <example>
      </example>
    </func>
    <func name="stopMonitoringFlash" access="Public">
      <self>
      </self>
      <summary>
      </summary>
      <returns>
      </returns>
      <example>
      </example>
      <param name="disconnected">
      </param>
    </func>
    <func name="flashRumbleLoop" access="Public">
      <self>
      </self>
      <summary>
      </summary>
      <returns>
      </returns>
      <example>
      </example>
      <param name="duration">
      </param>
    </func>
    <func name="monitorFlash" access="Public">
      <self>
      </self>
      <summary>
      </summary>
      <returns>
      </returns>
      <example>
      </example>
    </func>
    <func name="applyFlash" access="Public">
      <self>
      </self>
      <summary>
      </summary>
      <returns>
      </returns>
      <example>
      </example>
      <param name="duration">
      </param>
      <param name="rumbleduration">
      </param>
    </func>
    <func name="isFlashbanged" access="Public">
      <self>
      </self>
      <summary>
      </summary>
      <returns>
      </returns>
      <example>
      </example>
    </func>
    <func name="showstunflashMaskHud" access="Public">
      <self>
      </self>
      <summary>
      </summary>
      <returns>
      </returns>
      <example>
      </example>
    </func>
    <func name="clearstunflashMaskHud" access="Public">
      <self>
      </self>
      <summary>
      </summary>
      <returns>
      </returns>
      <example>
      </example>
    </func>
  </content>
</scriptinfo>